MANIFEST.in
README.md
go2
go2.1
go2.py
go2.sh
osfs.py
setup.py
version.py
go2.egg-info/PKG-INFO
go2.egg-info/SOURCES.txt
go2.egg-info/dependency_links.txt
go2.egg-info/top_level.txt