Metadata-Version: 2.1
Name: go2
Version: 2.20201116.1
Summary: go2 directory finder
Home-page: https://bitbucket.org/DavidVilla/go2
Author: David Villa Alises
Author-email: David.Villa@gmail.com
License: GPL v2 or later
Platform: UNKNOWN
Classifier: Programming Language :: Python :: 3
